django_short_url/__init__.py
django_short_url/admin.py
django_short_url/models.py
django_short_url/tests.py
django_short_url/urls.py
django_short_url/views.py
django_short_url/migrations/0001_initial.py
django_short_url/migrations/0002_auto_20180107_2226.py
django_short_url/migrations/0003_auto_20201130_0214.py
django_short_url/migrations/__init__.py
django_short_url/templates/django_short_url/errmsg.html
django_short_url-1.1.8.dist-info/METADATA
django_short_url-1.1.8.dist-info/WHEEL
django_short_url-1.1.8.dist-info/top_level.txt
django_short_url-1.1.8.dist-info/RECORD
