Metadata-Version: 2.1
Name: django-short-url
Version: 1.1.8
Summary: Django Short URL
Home-page: https://github.com/django-xxx/django-short-url
Author: Hackathon
Author-email: kimi.huang@brightcells.com
Keywords: django-short-url
Classifier: Development Status :: 5 - Production/Stable
Classifier: Environment :: Web Environment
Classifier: Framework :: Django
Classifier: Intended Audience :: Developers
Classifier: Programming Language :: Python
Classifier: Topic :: Software Development :: Libraries :: Python Modules
Classifier: Topic :: Office/Business :: Financial :: Spreadsheet
Requires-Dist: CodeConvert
Requires-Dist: TimeConvert
Requires-Dist: django-admin (>=1.2.4)
Requires-Dist: django-models-ext (>=1.1.10)
Requires-Dist: django-six
Requires-Dist: furl
Requires-Dist: shortuuid
